uiautomator2/.DS_Store
uiautomator2/__init__.py
uiautomator2/__main__.py
uiautomator2/_proto.py
uiautomator2/_selector.py
uiautomator2/abcd.py
uiautomator2/exceptions.py
uiautomator2/image.py
uiautomator2/init.py
uiautomator2/kp_u2_util.py
uiautomator2/messagebox.py
uiautomator2/screenrecord.py
uiautomator2/settings.py
uiautomator2/swipe.py
uiautomator2/utils.py
uiautomator2/version.py
uiautomator2/watcher.py
uiautomator2/webview.py
uiautomator2/widget.py
uiautomator2/xpath.py
uiautomator2/xpath_util.py
uiautomator2/assets/.DS_Store
uiautomator2/assets/__init__.py
uiautomator2/assets/utest-agent
uiautomator2/assets/utest-agent-64
uiautomator2/ext/__init__.py
uiautomator2/ext/htmlreport/README.md
uiautomator2/ext/htmlreport/__init__.py
uiautomator2/ext/htmlreport/assets/index.html
uiautomator2/ext/htmlreport/assets/pig.jpg
uiautomator2/ext/htmlreport/assets/simplehttpserver.py
uiautomator2/ext/htmlreport/assets/start.bat
uiautomator2/ext/info/__init__.py
uiautomator2/ext/info/conf.py
uiautomator2/ext/perf/README.md
uiautomator2/ext/perf/__init__.py
uiautomator2/ext/perf/net.png
uiautomator2/ext/perf/summary.png
uiautomator2/ext/xpath/README.md
uiautomator2/ext/xpath/__init__.py
uiautomator2/ext-archived/__init__.py
uiautomator2/ext-archived/aircv/README.md
uiautomator2/ext-archived/aircv/__init__.py
uiautomator2/ext-archived/ocr/README.md
uiautomator2/ext-archived/ocr/__init__.py
uiautomator2/ext-archived/ocr/baidu_ocr.py
utest_uiautomator2-2.16.17.dev44.dist-info/licenses/AUTHORS
utest_uiautomator2-2.16.17.dev44.dist-info/licenses/LICENSE
utest_uiautomator2-2.16.17.dev44.dist-info/METADATA
utest_uiautomator2-2.16.17.dev44.dist-info/WHEEL
utest_uiautomator2-2.16.17.dev44.dist-info/top_level.txt
utest_uiautomator2-2.16.17.dev44.dist-info/RECORD
