Metadata-Version: 2.4
Name: utest-uiautomator2
Version: 2.16.17.dev44
Summary: Python Wrapper for Google Android UiAutomator2 test tool
Author: codeskyblue
Author-email: codeskyblue@gmail.com
License: MIT
Classifier: Development Status :: 4 - Beta
Classifier: Environment :: Console
Classifier: Intended Audience :: Developers
Classifier: Operating System :: POSIX
Classifier: Programming Language :: Python :: 3
Classifier: Topic :: Software Development :: Libraries :: Python Modules
Classifier: Topic :: Software Development :: Testing
Requires-Python: >=3.6
License-File: LICENSE
License-File: AUTHORS
Dynamic: license-file
Dynamic: requires-python
